{
  "connections": {
    "categories": [
      {
        "name": "كَلِمَات تَدُلُّ عَلَى فَتَرَاتٍ زَمَنِيَّة",
        "nameEn": "Words denoting specific periods of time",
        "color": "yellow",
        "items": [
          {
            "ar": "يَوْمًا",
            "en": "a day",
            "ref": "76:10",
            "verse": "إِنَّا نَخَافُ مِن رَّبِّنَا يَوْمًا عَبُوسًۭا قَمْطَرِيرًۭا",
            "verseEn": "Indeed, We fear from our Lord a Day austere and distressful.\""
          },
          {
            "ar": "نَهَارًا",
            "en": "daytime",
            "ref": "71:5",
            "verse": "قَالَ رَبِّ إِنِّى دَعَوْتُ قَوْمِى لَيْلًۭا وَنَهَارًۭا",
            "verseEn": "He said, \"My Lord, indeed I invited my people [to truth] night and day."
          },
          {
            "ar": "غَدًا",
            "en": "tomorrow",
            "ref": "18:23",
            "verse": "وَلَا تَقُولَنَّ لِشَا۟ىْءٍ إِنِّى فَاعِلٌۭ ذَٰلِكَ غَدًا",
            "verseEn": "And never say of anything, \"Indeed, I will do that tomorrow,\""
          },
          {
            "ar": "عَامٍ",
            "en": "a year",
            "ref": "2:259",
            "verse": "أَوْ كَٱلَّذِى مَرَّ عَلَىٰ قَرْيَةٍۢ وَهِىَ خَاوِيَةٌ عَلَىٰ عُرُوشِهَا قَالَ أَنَّىٰ يُحْىِۦ هَـٰذِهِ ٱللَّهُ بَعْدَ مَوْتِهَا ۖ فَأَمَاتَهُ ٱللَّهُ مِا۟ئَةَ عَامٍۢ ثُمَّ بَعَثَهُۥ ۖ قَالَ كَمْ لَبِثْتَ ۖ قَالَ لَبِثْتُ يَوْمًا أَوْ بَعْضَ يَوْمٍۢ ۖ قَالَ بَل لَّبِثْتَ مِا۟ئَةَ عَامٍۢ فَٱنظُرْ إِلَىٰ طَعَامِكَ وَشَرَابِكَ لَمْ يَتَسَنَّهْ ۖ وَٱنظُرْ إِلَىٰ حِمَارِكَ وَلِنَجْعَلَكَ ءَايَةًۭ لِّلنَّاسِ ۖ وَٱنظُرْ إِلَى ٱلْعِظَامِ كَيْفَ نُنشِزُهَا ثُمَّ نَكْسُوهَا لَحْمًۭا ۚ فَلَمَّا تَبَيَّنَ لَهُۥ قَالَ أَعْلَمُ أَنَّ ٱللَّهَ عَلَىٰ كُلِّ شَىْءٍۢ قَدِيرٌۭ",
            "verseEn": "Or [consider such an example] as the one who passed by a township which had fallen into ruin. He said, \"How will Allāh bring this to life after its death?\" So Allāh caused him to die for a hundred years; then He revived him. He said, \"How long have you remained?\" He [the man] said, \"I have remained a day or part of a day.\" He said, \"Rather, you have remained one hundred years. Look at your food and your drink; it has not changed with time. And look at your donkey; and We will make you a sign for the people. And look at the bones [of this donkey] - how We raise them and then We cover them with flesh.\" And when it became clear to him, he said, \"I know that Allāh is over all things competent.\""
          }
        ]
      },
      {
        "name": "كَلِمَاتٌ تَبْدَأُ بِأَدَاةِ الِاسْتِفْهَامِ 'أَفَ'",
        "nameEn": "Words that begin with the interrogative prefix 'Afa-' (أَف)",
        "color": "green",
        "items": [
          {
            "ar": "أَفَلَا",
            "en": "Then do not...?",
            "ref": "6:50",
            "verse": "قُل لَّآ أَقُولُ لَكُمْ عِندِى خَزَآئِنُ ٱللَّهِ وَلَآ أَعْلَمُ ٱلْغَيْبَ وَلَآ أَقُولُ لَكُمْ إِنِّى مَلَكٌ ۖ إِنْ أَتَّبِعُ إِلَّا مَا يُوحَىٰٓ إِلَىَّ ۚ قُلْ هَلْ يَسْتَوِى ٱلْأَعْمَىٰ وَٱلْبَصِيرُ ۚ أَفَلَا تَتَفَكَّرُونَ",
            "verseEn": "Say, [O Muḥammad], \"I do not tell you that I have the depositories [containing the provision] of Allāh or that I know the unseen, nor do I tell you that I am an angel. I only follow what is revealed to me.\" Say, \"Is the blind equivalent to the seeing? Then will you not give thought?\""
          },
          {
            "ar": "أَفَبِعَذَابِنَا",
            "en": "So is it Our punishment...?",
            "ref": "26:204",
            "verse": "أَفَبِعَذَابِنَا يَسْتَعْجِلُونَ",
            "verseEn": "So for Our punishment are they impatient?"
          },
          {
            "ar": "أَفَمَن",
            "en": "So is one whose...?",
            "ref": "39:22",
            "verse": "أَفَمَن شَرَحَ ٱللَّهُ صَدْرَهُۥ لِلْإِسْلَـٰمِ فَهُوَ عَلَىٰ نُورٍۢ مِّن رَّبِّهِۦ ۚ فَوَيْلٌۭ لِّلْقَـٰسِيَةِ قُلُوبُهُم مِّن ذِكْرِ ٱللَّهِ ۚ أُو۟لَـٰٓئِكَ فِى ضَلَـٰلٍۢ مُّبِينٍ",
            "verseEn": "So is one whose breast Allāh has expanded to [accept] Islām and he is upon [i.e., guided by] a light from his Lord [like one whose heart rejects it]? Then woe to those whose hearts are hardened against the remembrance of Allāh. Those are in manifest error."
          },
          {
            "ar": "أَفَأَصْفَىٰكُمْ",
            "en": "Then has He preferred you...?",
            "ref": "17:40",
            "verse": "أَفَأَصْفَىٰكُمْ رَبُّكُم بِٱلْبَنِينَ وَٱتَّخَذَ مِنَ ٱلْمَلَـٰٓئِكَةِ إِنَـٰثًا ۚ إِنَّكُمْ لَتَقُولُونَ قَوْلًا عَظِيمًۭا",
            "verseEn": "Then, has your Lord chosen you for [having] sons and taken [i.e., adopted] from among the angels daughters? Indeed, you say a grave saying."
          }
        ]
      },
      {
        "name": "مَصَادِرٌ اسْتُعْمِلَتْ لِلْوَصْفِ",
        "nameEn": "Verbal nouns (maṣdar) used adjectivally to describe an entity",
        "color": "blue",
        "items": [
          {
            "ar": "عَدْلٍ",
            "en": "justice",
            "ref": "65:2",
            "verse": "فَإِذَا بَلَغْنَ أَجَلَهُنَّ فَأَمْسِكُوهُنَّ بِمَعْرُوفٍ أَوْ فَارِقُوهُنَّ بِمَعْرُوفٍۢ وَأَشْهِدُوا۟ ذَوَىْ عَدْلٍۢ مِّنكُمْ وَأَقِيمُوا۟ ٱلشَّهَـٰدَةَ لِلَّهِ ۚ ذَٰلِكُمْ يُوعَظُ بِهِۦ مَن كَانَ يُؤْمِنُ بِٱللَّهِ وَٱلْيَوْمِ ٱلْـَٔاخِرِ ۚ وَمَن يَتَّقِ ٱللَّهَ يَجْعَل لَّهُۥ مَخْرَجًۭا",
            "verseEn": "And when they have [nearly] fulfilled their term, either retain them according to acceptable terms or part with them according to acceptable terms. And bring to witness two just men from among you and establish the testimony for [the acceptance of] Allāh. That is instructed to whoever should believe in Allāh and the Last Day. And whoever fears Allāh - He will make for him a way out"
          },
          {
            "ar": "طِفْلًا",
            "en": "a child",
            "ref": "40:67",
            "verse": "هُوَ ٱلَّذِى خَلَقَكُم مِّن تُرَابٍۢ ثُمَّ مِن نُّطْفَةٍۢ ثُمَّ مِنْ عَلَقَةٍۢ ثُمَّ يُخْرِجُكُمْ طِفْلًۭا ثُمَّ لِتَبْلُغُوٓا۟ أَشُدَّكُمْ ثُمَّ لِتَكُونُوا۟ شُيُوخًۭا ۚ وَمِنكُم مَّن يُتَوَفَّىٰ مِن قَبْلُ ۖ وَلِتَبْلُغُوٓا۟ أَجَلًۭا مُّسَمًّۭى وَلَعَلَّكُمْ تَعْقِلُونَ",
            "verseEn": "It is He who created you from dust, then from a sperm-drop, then from a clinging clot; then He brings you out as a child; then [He develops you] that you reach your [time of] maturity, then [further] that you become elders. And among you is he who is taken in death before [that], so that you reach a specified term; and perhaps you will use reason."
          },
          {
            "ar": "ضَيْفِى",
            "en": "my guests",
            "ref": "15:68",
            "verse": "قَالَ إِنَّ هَـٰٓؤُلَآءِ ضَيْفِى فَلَا تَفْضَحُونِ",
            "verseEn": "[Lot] said, \"Indeed, these are my guests, so do not shame me."
          },
          {
            "ar": "كَذِبٍ",
            "en": "falsehood",
            "ref": "12:18",
            "verse": "وَجَآءُو عَلَىٰ قَمِيصِهِۦ بِدَمٍۢ كَذِبٍۢ ۚ قَالَ بَلْ سَوَّلَتْ لَكُمْ أَنفُسُكُمْ أَمْرًۭا ۖ فَصَبْرٌۭ جَمِيلٌۭ ۖ وَٱللَّهُ ٱلْمُسْتَعَانُ عَلَىٰ مَا تَصِفُونَ",
            "verseEn": "And they brought upon his shirt false blood. [Jacob] said, \"Rather, your souls have enticed you to something, so patience is most fitting. And Allāh is the one sought for help against that which you describe.\""
          }
        ]
      },
      {
        "name": "أَسْمَاءٌ مَنْصُوبَةٌ عَلَى التَّمْيِيزِ",
        "nameEn": "Nouns in the accusative case functioning as a specification (Tamyīz)",
        "color": "purple",
        "items": [
          {
            "ar": "نَفَرًا",
            "en": "in followers",
            "ref": "18:34",
            "verse": "وَكَانَ لَهُۥ ثَمَرٌۭ فَقَالَ لِصَـٰحِبِهِۦ وَهُوَ يُحَاوِرُهُۥٓ أَنَا۠ أَكْثَرُ مِنكَ مَالًۭا وَأَعَزُّ نَفَرًۭا",
            "verseEn": "And he had fruit, so he said to his companion while he was conversing with him, \"I am greater than you in wealth and mightier in [numbers of] men.\""
          },
          {
            "ar": "حَٰفِظًا",
            "en": "as a guardian",
            "ref": "12:64",
            "verse": "قَالَ هَلْ ءَامَنُكُمْ عَلَيْهِ إِلَّا كَمَآ أَمِنتُكُمْ عَلَىٰٓ أَخِيهِ مِن قَبْلُ ۖ فَٱللَّهُ خَيْرٌ حَـٰفِظًۭا ۖ وَهُوَ أَرْحَمُ ٱلرَّٰحِمِينَ",
            "verseEn": "He said, \"Should I entrust you with him except [under coercion] as I entrusted you with his brother before? But Allāh is the best guardian, and He is the most merciful of the merciful.\""
          },
          {
            "ar": "صِبْغَةً",
            "en": "in creed",
            "ref": "2:138",
            "verse": "صِبْغَةَ ٱللَّهِ ۖ وَمَنْ أَحْسَنُ مِنَ ٱللَّهِ صِبْغَةًۭ ۖ وَنَحْنُ لَهُۥ عَـٰبِدُونَ",
            "verseEn": "[And say, \"Ours is] the religion of Allāh. And who is better than Allāh in [ordaining] religion? And we are worshippers of Him.\""
          },
          {
            "ar": "أَعْمَٰلًا",
            "en": "in deeds",
            "ref": "18:103",
            "verse": "قُلْ هَلْ نُنَبِّئُكُم بِٱلْأَخْسَرِينَ أَعْمَـٰلًا",
            "verseEn": "Say, [O Muḥammad], \"Shall we [believers] inform you of the greatest losers as to [their] deeds?"
          }
        ]
      }
    ]
  },
  "harf": {
    "word": "روح",
    "display": "رُوح",
    "hint": "The divine breath or command; Jibril is known as the faithful one.",
    "verseRef": "21:91",
    "arabicVerse": "وَٱلَّتِىٓ أَحْصَنَتْ فَرْجَهَا فَنَفَخْنَا فِيهَا مِن رُّوحِنَا وَجَعَلْنَـٰهَا وَٱبْنَهَآ ءَايَةًۭ لِّلْعَـٰلَمِينَ",
    "verse": "21:91 — And [mention] the one who guarded her chastity [i.e., Mary], so We blew into her [garment] through Our angel [i.e., Gabriel], and We made her and her son a sign for the worlds."
  },
  "deduction": {
    "title": "The Test of Unwavering Submission",
    "intro": "A young soul is placed at the heart of an immense trial, a test of faith not just for this individual, but for their devoted parent as well. This moment of profound submission would echo through history, its legacy commemorated by millions. Who is this figure of patience and obedience?",
    "clues": [
      "I was left with my mother in a barren valley, a place with no vegetation or water.",
      "In our desperation, a miraculous spring of water gushed forth from the earth to sustain us.",
      "With my father, I raised the foundations of a sacred House, a focal point of worship for all humanity.",
      "My father saw in a dream that he was to sacrifice me, a divine command that tested us both.",
      "When my father told me of his vision, I replied, 'O my father, do as you are commanded. You will find me, if Allah wills, of the steadfast.'",
      "Allah ransomed me with a great sacrifice, and this act of submission is commemorated annually by believers."
    ],
    "categories": {
      "identity": {
        "label": "Who Am I?",
        "options": [
          "Prophet Isma'il",
          "Prophet Yahya",
          "Prophet Yusuf",
          "Prophet Ishaq",
          "Qabil"
        ],
        "answer": "Prophet Isma'il"
      },
      "trial": {
        "label": "The Divine Test",
        "options": [
          "A father's vision to sacrifice his son",
          "Building an ark to survive a flood",
          "Being thrown into a fire by a tyrant",
          "Being swallowed by a giant fish",
          "Accusation of theft by one's own siblings"
        ],
        "answer": "A father's vision to sacrifice his son"
      },
      "location": {
        "label": "Key Element",
        "options": [
          "A spring of water",
          "A staff that turned into a serpent",
          "A feast sent down from the heavens",
          "A camel emerging from a rock",
          "A shirt that healed blindness"
        ],
        "answer": "A spring of water"
      },
      "outcome": {
        "label": "Outcome",
        "options": [
          "Ransomed with a great sacrifice",
          "The fire became cool and peaceful",
          "The sea parted to create a dry path",
          "Given kingship over a vast domain",
          "Elected as a leader by the people"
        ],
        "answer": "Ransomed with a great sacrifice"
      }
    },
    "verseRef": "14:39",
    "arabic": "ٱلْحَمْدُ لِلَّهِ ٱلَّذِى وَهَبَ لِى عَلَى ٱلْكِبَرِ إِسْمَـٰعِيلَ وَإِسْحَـٰقَ ۚ إِنَّ رَبِّى لَسَمِيعُ ٱلدُّعَآءِ",
    "verse": "Praise to Allāh, who has granted to me in old age Ishmael and Isaac. Indeed, my Lord is the Hearer of supplication. (14:39)"
  },
  "scramble": {
    "verseRef": "10:62",
    "reference": "Surah Yunus (10:62)",
    "segments": [
      "أَلَآ إِنَّ أَوْلِيَآءَ ٱللَّهِ",
      "لَا خَوْفٌ عَلَيْهِمْ",
      "وَلَا هُمْ",
      "يَحْزَنُونَ"
    ],
    "translations": [
      "No doubt Indeed (the) friends",
      "(of) Allah (there will be) no fear",
      "upon then and not",
      "they will grieve"
    ],
    "hint": "A divine promise of peace and security for those who are close to Him, protecting them from fear of the future and grief for the past.",
    "arabic": "أَلَآ إِنَّ أَوْلِيَآءَ ٱللَّهِ لَا خَوْفٌ عَلَيْهِمْ وَلَا هُمْ يَحْزَنُونَ",
    "words": [
      "أَلَآ إِنَّ أَوْلِيَآءَ",
      "ٱللَّهِ لَا خَوْفٌ",
      "عَلَيْهِمْ وَلَا",
      "هُمْ يَحْزَنُونَ"
    ],
    "verseEn": "Unquestionably, [for] the allies of Allāh there will be no fear concerning them, nor will they grieve -"
  }
}